{"value":[{"symbol":"ILVUSDT","sumOpenInterest":"224205.30000000","sumOpenInterestValue":"3269987.99313734","CMCCirculatingSupply":"6340247.61132278","timestamp":1758132000000},{"symbol":"ILVUSDT","sumOpenInterest":"220996.90000000","sumOpenInterestValue":"3227659.72450000","CMCCirculatingSupply":"6340247.61132278","timestamp":1758135600000},{"symbol":"ILVUSDT","sumOpenInterest":"222490.50000000","sumOpenInterestValue":"3338556.56137694","CMCCirculatingSupply":"6340247.61132278","timestamp":1758139200000},{"symbol":"ILVUSDT","sumOpenInterest":"224680.80000000","sumOpenInterestValue":"3347366.96178780","CMCCirculatingSupply":"6340247.61132278","timestamp":1758142800000},{"symbol":"ILVUSDT","sumOpenInterest":"225300.20000000","sumOpenInterestValue":"3410618.75326259","CMCCirculatingSupply":"6340247.61132278","timestamp":1758146400000},{"symbol":"ILVUSDT","sumOpenInterest":"225718.10000000","sumOpenInterestValue":"3456643.92491975","CMCCirculatingSupply":"6340247.61132278","timestamp":1758150000000},{"symbol":"ILVUSDT","sumOpenInterest":"227348.50000000","sumOpenInterestValue":"3473132.94068397","CMCCirculatingSupply":"6340247.61132278","timestamp":1758153600000},{"symbol":"ILVUSDT","sumOpenInterest":"227979.10000000","sumOpenInterestValue":"3461406.67530000","CMCCirculatingSupply":"6340247.61132278","timestamp":1758157200000},{"symbol":"ILVUSDT","sumOpenInterest":"227384.20000000","sumOpenInterestValue":"3464325.45388769","CMCCirculatingSupply":"6340247.61132278","timestamp":1758160800000},{"symbol":"ILVUSDT","sumOpenInterest":"227239.00000000","sumOpenInterestValue":"3467667.14000000","CMCCirculatingSupply":"6340492.45080628","timestamp":1758164400000},{"symbol":"ILVUSDT","sumOpenInterest":"228717.50000000","sumOpenInterestValue":"3505661.77932273","CMCCirculatingSupply":"6340492.45080628","timestamp":1758168000000},{"symbol":"ILVUSDT","sumOpenInterest":"229474.10000000","sumOpenInterestValue":"3519673.74580000","CMCCirculatingSupply":"6340492.45080628","timestamp":1758171600000},{"symbol":"ILVUSDT","sumOpenInterest":"230544.10000000","sumOpenInterestValue":"3517180.78960000","CMCCirculatingSupply":"6340492.45080628","timestamp":1758175200000},{"symbol":"ILVUSDT","sumOpenInterest":"229471.60000000","sumOpenInterestValue":"3468556.66565666","CMCCirculatingSupply":"6340492.45080628","timestamp":1758178800000},{"symbol":"ILVUSDT","sumOpenInterest":"229242.90000000","sumOpenInterestValue":"3478797.06282331","CMCCirculatingSupply":"6340492.45080628","timestamp":1758182400000},{"symbol":"ILVUSDT","sumOpenInterest":"228924.30000000","sumOpenInterestValue":"3492186.19554687","CMCCirculatingSupply":"6340492.45080628","timestamp":1758186000000},{"symbol":"ILVUSDT","sumOpenInterest":"229268.10000000","sumOpenInterestValue":"3497003.97336757","CMCCirculatingSupply":"6340492.45080628","timestamp":1758189600000},{"symbol":"ILVUSDT","sumOpenInterest":"227687.60000000","sumOpenInterestValue":"3463841.92340088","CMCCirculatingSupply":"6340492.45080628","timestamp":1758193200000},{"symbol":"ILVUSDT","sumOpenInterest":"228935.00000000","sumOpenInterestValue":"3489422.95915395","CMCCirculatingSupply":"6340492.45080628","timestamp":1758196800000},{"symbol":"ILVUSDT","sumOpenInterest":"228240.10000000","sumOpenInterestValue":"3503723.00284724","CMCCirculatingSupply":"6340492.45080628","timestamp":1758200400000},{"symbol":"ILVUSDT","sumOpenInterest":"227333.70000000","sumOpenInterestValue":"3513153.50148748","CMCCirculatingSupply":"6340492.45080628","timestamp":1758204000000},{"symbol":"ILVUSDT","sumOpenInterest":"229259.70000000","sumOpenInterestValue":"3559462.89194797","CMCCirculatingSupply":"6340492.45080628","timestamp":1758207600000},{"symbol":"ILVUSDT","sumOpenInterest":"229747.00000000","sumOpenInterestValue":"3568660.15100000","CMCCirculatingSupply":"6340492.45080628","timestamp":1758211200000},{"symbol":"ILVUSDT","sumOpenInterest":"230248.70000000","sumOpenInterestValue":"3594872.95310000","CMCCirculatingSupply":"6340492.45080628","timestamp":1758214800000}],"timestamp":1758215845619,"ttl":3600000}